WdbDrive/__init__.py
WdbDrive/drive.py
WdbDrive-0.1.1.dist-info/METADATA
WdbDrive-0.1.1.dist-info/WHEEL
WdbDrive-0.1.1.dist-info/top_level.txt
WdbDrive-0.1.1.dist-info/RECORD
